rlh/__init__.py
rlh/handlers.py
redis_logs-1.2.0.dist-info/LICENSE
redis_logs-1.2.0.dist-info/METADATA
redis_logs-1.2.0.dist-info/WHEEL
redis_logs-1.2.0.dist-info/top_level.txt
redis_logs-1.2.0.dist-info/RECORD
