Metadata-Version: 2.1
Name: redis-logs
Version: 1.2.0
Summary: Python log handler to forward logs to Redis database
Home-page: https://github.com/Iglesys347/redis-log-handler
Author: Iglesys347
Author-email: g.imbert34@gmail.com
License: MIT
Project-URL: Documentation, https://redis-log-handler.readthedocs.io/en/latest
Project-URL: Changes, https://github.com/Iglesys347/redis-log-handler/releases
Project-URL: Code, https://github.com/Iglesys347/redis-log-handler
Project-URL: Issue tracker, https://github.com/Iglesys347/redis-log-handler/issues
Keywords: Redis,logging
Platform: UNKNOWN
Classifier: Development Status :: 5 - Production/Stable
Classifier: Environment :: Console
Classifier: Intended Audience :: Developers
Classifier: License :: OSI Approved :: MIT License
Classifier: Operating System :: OS Independent
Classifier: Programming Language :: Python
Classifier: Programming Language :: Python :: 3
Classifier: Programming Language :: Python :: 3 :: Only
Classifier: Programming Language :: Python :: 3.9
Classifier: Programming Language :: Python :: 3.10
Classifier: Programming Language :: Python :: 3.11
Requires-Python: >=3.9
License-File: LICENSE
Requires-Dist: redis
